aiiiSharedPython/__init__.py
aiiiSharedPython/module.py
aiiiSharedPython-0.0.8.dist-info/METADATA
aiiiSharedPython-0.0.8.dist-info/WHEEL
aiiiSharedPython-0.0.8.dist-info/top_level.txt
aiiiSharedPython-0.0.8.dist-info/RECORD
