Metadata-Version: 2.1
Name: aiiiSharedPython
Version: 0.0.8
Summary: Aiii Shared Package
Home-page: https://github.com/ranger1214v/aiii-shared-python
Author: Ranger
Author-email: ranger1214v@gmail.com
Requires-Dist: requests
